{"/var/home/marc/Documents/quantum/trbo/comparisons/synth_benchmarks/cch.qasm": {"input": "/var/home/marc/Documents/quantum/trbo/comparisons/synth_benchmarks/cch.qasm", "output": "/var/home/marc/Documents/quantum/trbo/comparisons/synth_benchmarks/outputs/..", "name": "cch", "num_qudits": 3, "og_data": {"dist": 0.0, "rz": 0, "clifford": 20, "t": 9, "unknown": 0, "qubit_count": [20, 9], "time": 0}, "leap": {"dist": 0.0, "rz": 45, "clifford": 36, "t": 0, "unknown": 0, "qubit_count": [75, 6], "gridsynth_time": 10.961480797996046, "gridsynth_dist": 0.0018602167919658278, "gridsynth_t": 730, "gridsynth_clifford": 1203, "time": 32.210483339993516}, "leap+trbo": {"dist": 2.1073424255447017e-08, "rz": 0, "clifford": 64, "t": 9, "unknown": 0, "qubit_count": [67, 6], "time": 63.39589133000118}, "leap+trbo-slow": {"dist": 2.1073424255447017e-08, "rz": 0, "clifford": 62, "t": 9, "unknown": 0, "qubit_count": [65, 6], "time": 118.29934163700091}, "leap+trbo-fast": {"dist": 2.5809568279517847e-08, "rz": 0, "clifford": 63, "t": 13, "unknown": 0, "qubit_count": [70, 6], "time": 17.008767000006628}}, "/var/home/marc/Documents/quantum/trbo/comparisons/synth_benchmarks/ccx.qasm": {"input": "/var/home/marc/Documents/quantum/trbo/comparisons/synth_benchmarks/ccx.qasm", "output": "/var/home/marc/Documents/quantum/trbo/comparisons/synth_benchmarks/outputs/..", "name": "ccx", "num_qudits": 3, "og_data": {"dist": 0.0, "rz": 0, "clifford": 8, "t": 7, "unknown": 0, "qubit_count": [9, 6], "time": 0}, "leap": {"dist": 0.0, "rz": 57, "clifford": 46, "t": 0, "unknown": 0, "qubit_count": [95, 8], "gridsynth_time": 10.884662726995884, "gridsynth_dist": 0.0016946148467007832, "gridsynth_t": 638, "gridsynth_clifford": 1116, "time": 33.288097062002635}, "leap+trbo": {"dist": 2.1073424255447017e-08, "rz": 0, "clifford": 89, "t": 9, "unknown": 0, "qubit_count": [90, 8], "time": 99.78540293200058}, "leap+trbo-slow": {"dist": 2.1073424255447017e-08, "rz": 0, "clifford": 81, "t": 19, "unknown": 0, "qubit_count": [92, 8], "time": 180.08156607799174}, "leap+trbo-fast": {"dist": 2.1073424255447017e-08, "rz": 0, "clifford": 78, "t": 19, "unknown": 0, "qubit_count": [89, 8], "time": 28.569698785009678}}, "/var/home/marc/Documents/quantum/trbo/comparisons/synth_benchmarks/rcccx.qasm": {"input": "/var/home/marc/Documents/quantum/trbo/comparisons/synth_benchmarks/rcccx.qasm", "output": "/var/home/marc/Documents/quantum/trbo/comparisons/synth_benchmarks/outputs/..", "name": "rcccx", "num_qudits": 4, "og_data": {"dist": 0.0, "rz": 0, "clifford": 19, "t": 9, "unknown": 0, "qubit_count": [15, 13], "time": 0}, "leap": {"dist": 1.1733186057227569e-07, "rz": 60, "clifford": 48, "t": 0, "unknown": 0, "qubit_count": [100, 8], "gridsynth_time": 11.370425692002755, "gridsynth_dist": 0.0024146680921208474, "gridsynth_t": 886, "gridsynth_clifford": 1490, "time": 40.47094226500485}, "leap+trbo": {"dist": 1.228781230931777e-07, "rz": 0, "clifford": 91, "t": 21, "unknown": 0, "qubit_count": [104, 8], "time": 142.44774733899976}, "leap+trbo-slow": {"dist": 0.19938007031081229, "rz": 0, "clifford": 87, "t": 16, "unknown": 0, "qubit_count": [95, 8], "time": 309.3742806530063}, "leap+trbo-fast": {"dist": 1.219712610821791e-07, "rz": 0, "clifford": 80, "t": 21, "unknown": 0, "qubit_count": [93, 8], "time": 50.381809622005676}}, "/var/home/marc/Documents/quantum/trbo/comparisons/synth_benchmarks/cciswap.qasm": {"input": "/var/home/marc/Documents/quantum/trbo/comparisons/synth_benchmarks/cciswap.qasm", "output": "/var/home/marc/Documents/quantum/trbo/comparisons/synth_benchmarks/outputs/..", "name": "cciswap", "num_qudits": 4, "og_data": {"dist": 0.0, "rz": 0, "clifford": 51, "t": 20, "unknown": 0, "qubit_count": [39, 32], "time": 0}, "leap": {"dist": 0.0, "rz": 132, "clifford": 108, "t": 0, "unknown": 0, "qubit_count": [220, 20], "gridsynth_time": 11.969266387997777, "gridsynth_dist": 0.0032260125151379986, "gridsynth_t": 1854, "gridsynth_clifford": 3167, "time": 149.48121847899165}, "leap+trbo": {"dist": 3.332000937312528e-08, "rz": 23, "clifford": 186, "t": 31, "unknown": 0, "qubit_count": [220, 20], "gridsynth_time": 10.623774356994545, "gridsynth_dist": 0.001850930304338753, "gridsynth_t": 789, "gridsynth_clifford": 1397, "time": 311.40277660801075}, "leap+trbo-slow": {"dist": 0.0, "rz": 13, "clifford": 192, "t": 38, "unknown": 0, "qubit_count": [223, 20], "gridsynth_time": 9.381158462987514, "gridsynth_dist": 0.0015871593950184464, "gridsynth_t": 442, "gridsynth_clifford": 847, "time": 725.0080480370088}, "leap+trbo-fast": {"dist": 2.1073424255447017e-08, "rz": 26, "clifford": 181, "t": 13, "unknown": 0, "qubit_count": [200, 20], "gridsynth_time": 10.328202374003013, "gridsynth_dist": 0.002002934959224291, "gridsynth_t": 829, "gridsynth_clifford": 1456, "time": 166.48034372800612}}, "/var/home/marc/Documents/quantum/trbo/comparisons/synth_benchmarks/adder.qasm": {"input": "/var/home/marc/Documents/quantum/trbo/comparisons/synth_benchmarks/adder.qasm", "output": "/var/home/marc/Documents/quantum/trbo/comparisons/synth_benchmarks/outputs/..", "name": "adder", "num_qudits": 4, "og_data": {"dist": 0.0, "rz": 0, "clifford": 44, "t": 7, "unknown": 0, "qubit_count": [22, 29], "time": 0}, "leap": {"dist": 0.0, "rz": 90, "clifford": 73, "t": 0, "unknown": 0, "qubit_count": [150, 13], "gridsynth_time": 12.32639838400064, "gridsynth_dist": 0.0021353811127003512, "gridsynth_t": 948, "gridsynth_clifford": 1686, "time": 52.30522933299653}, "leap+trbo": {"dist": 2.1073424255447017e-08, "rz": 0, "clifford": 130, "t": 14, "unknown": 0, "qubit_count": [131, 13], "time": 321.0048632329999}, "leap+trbo-slow": {"dist": 2.1073424255447017e-08, "rz": 0, "clifford": 129, "t": 18, "unknown": 0, "qubit_count": [134, 13], "time": 539.2003528979985}, "leap+trbo-fast": {"dist": 2.1073424255447017e-08, "rz": 0, "clifford": 143, "t": 24, "unknown": 0, "qubit_count": [154, 13], "time": 33.62550488299166}}, "/var/home/marc/Documents/quantum/trbo/comparisons/synth_benchmarks/U1.qasm": {"input": "/var/home/marc/Documents/quantum/trbo/comparisons/synth_benchmarks/U1.qasm", "output": "/var/home/marc/Documents/quantum/trbo/comparisons/synth_benchmarks/outputs/..", "name": "U1", "num_qudits": 4, "og_data": {"dist": 0.0, "rz": 0, "clifford": 29, "t": 11, "unknown": 0, "qubit_count": [26, 14], "time": 0}, "leap": {"dist": 0.0, "rz": 96, "clifford": 78, "t": 0, "unknown": 0, "qubit_count": [160, 14], "gridsynth_time": 4.680607520000194, "gridsynth_dist": 0.002414292334576149, "gridsynth_t": 1082, "gridsynth_clifford": 1905, "time": 800.7236747580027}, "leap+trbo": {"dist": 2.1073424255447017e-08, "rz": 5, "clifford": 138, "t": 22, "unknown": 0, "qubit_count": [151, 14], "gridsynth_time": 3.332989432994509, "gridsynth_dist": 0.0009319070076634359, "gridsynth_t": 182, "gridsynth_clifford": 390, "time": 115.06152036100684}, "leap+trbo-slow": {"dist": 2.5809568279517847e-08, "rz": 6, "clifford": 142, "t": 31, "unknown": 0, "qubit_count": [165, 14], "gridsynth_time": 3.3573376089916565, "gridsynth_dist": 0.0009772297338478107, "gridsynth_t": 217, "gridsynth_clifford": 446, "time": 213.91947886699927}, "leap+trbo-fast": {"dist": 3.942476676500724e-08, "rz": 9, "clifford": 137, "t": 34, "unknown": 0, "qubit_count": [166, 14], "gridsynth_time": 3.46407060000638, "gridsynth_dist": 0.000887263064042819, "gridsynth_t": 326, "gridsynth_clifford": 581, "time": 65.01472107099835}}, "/var/home/marc/Documents/quantum/trbo/comparisons/synth_benchmarks/U1_var.qasm": {"input": "/var/home/marc/Documents/quantum/trbo/comparisons/synth_benchmarks/U1_var.qasm", "output": "/var/home/marc/Documents/quantum/trbo/comparisons/synth_benchmarks/outputs/..", "name": "U1_var", "num_qudits": 4, "og_data": {"dist": 0.0, "rz": 0, "clifford": 37, "t": 11, "unknown": 0, "qubit_count": [30, 18], "time": 0}, "leap": {"dist": 2.5809568279517847e-08, "rz": 108, "clifford": 88, "t": 0, "unknown": 0, "qubit_count": [180, 16], "gridsynth_time": 4.955709911999293, "gridsynth_dist": 0.0021689540120149796, "gridsynth_t": 1460, "gridsynth_clifford": 2513, "time": 37.59412945700751}, "leap+trbo": {"dist": 4.2146848510894035e-08, "rz": 2, "clifford": 152, "t": 39, "unknown": 0, "qubit_count": [177, 16], "gridsynth_time": 3.197135234993766, "gridsynth_dist": 0.0006892237385973214, "gridsynth_t": 103, "gridsynth_clifford": 257, "time": 122.2929191650037}, "leap+trbo-slow": {"dist": 4.2146848510894035e-08, "rz": 0, "clifford": 162, "t": 28, "unknown": 0, "qubit_count": [174, 16], "time": 310.6331742730108}, "leap+trbo-fast": {"dist": 4.712160915387242e-08, "rz": 0, "clifford": 161, "t": 42, "unknown": 0, "qubit_count": [187, 16], "time": 59.195377238997025}}, "/var/home/marc/Documents/quantum/trbo/comparisons/synth_benchmarks/U2.qasm": {"input": "/var/home/marc/Documents/quantum/trbo/comparisons/synth_benchmarks/U2.qasm", "output": "/var/home/marc/Documents/quantum/trbo/comparisons/synth_benchmarks/outputs/..", "name": "U2", "num_qudits": 4, "og_data": {"dist": 0.0, "rz": 0, "clifford": 50, "t": 7, "unknown": 0, "qubit_count": [29, 28], "time": 0}, "leap": {"dist": 0.0, "rz": 90, "clifford": 73, "t": 0, "unknown": 0, "qubit_count": [150, 13], "gridsynth_time": 4.905196760999388, "gridsynth_dist": 0.002909997970788736, "gridsynth_t": 1402, "gridsynth_clifford": 2354, "time": 25.309298213003785}, "leap+trbo": {"dist": 0.0, "rz": 0, "clifford": 128, "t": 28, "unknown": 0, "qubit_count": [143, 13], "time": 97.36532694099878}, "leap+trbo-slow": {"dist": 2.1073424255447017e-08, "rz": 0, "clifford": 136, "t": 24, "unknown": 0, "qubit_count": [147, 13], "time": 203.13858024300134}, "leap+trbo-fast": {"dist": 2.1073424255447017e-08, "rz": 0, "clifford": 129, "t": 30, "unknown": 0, "qubit_count": [146, 13], "time": 30.96584499400342}}}